utils_tdinoto/__init__.py
utils_tdinoto/numeric.py
utils_tdinoto/utils_bids_dcm_dataset.py
utils_tdinoto/utils_dict.py
utils_tdinoto/utils_io.py
utils_tdinoto/utils_lists.py
utils_tdinoto/utils_nifti_dicom.py
utils_tdinoto/utils_numpy.py
utils_tdinoto/utils_plots.py
utils_tdinoto/utils_strings.py
python3_utils_tdinoto-1.0.13.dist-info/LICENSE
python3_utils_tdinoto-1.0.13.dist-info/METADATA
python3_utils_tdinoto-1.0.13.dist-info/WHEEL
python3_utils_tdinoto-1.0.13.dist-info/top_level.txt
python3_utils_tdinoto-1.0.13.dist-info/RECORD
