Metadata-Version: 2.1
Name: python3_utils_tdinoto
Version: 1.0.13
Summary: Useful wrapper functions for the most common python data types, and for nifti/dicom arrays.
Author-email: Tommaso Di Noto <tommydino@hotmail.it>
License: MIT License
Project-URL: Homepage, https://github.com/tommydino93/python3_utils_tdinoto
Keywords: utils,wrappers
Classifier: License :: OSI Approved :: MIT License
Classifier: Programming Language :: Python
Classifier: Programming Language :: Python :: 3
Requires-Python: >=3.7
License-File: LICENSE
Requires-Dist: nibabel
Requires-Dist: SimpleITK
Requires-Dist: python-dateutil
Requires-Dist: torch
